complexcgr/__init__.py
complexcgr/cgr.py
complexcgr/complexcgr.py
complexcgr/complexfcgr.py
complexcgr/fcgr.py
complexcgr/fcgr_kmc.py
complexcgr/fcgr_samples.py
complexcgr/icgr.py
complexcgr-0.8.0.dist-info/LICENSE
complexcgr-0.8.0.dist-info/METADATA
complexcgr-0.8.0.dist-info/WHEEL
complexcgr-0.8.0.dist-info/RECORD
